{
  "participants": {
    "player": "019bbf47-9e25-72a2-b58a-407e9817c7ad"
  },
  "results": [
    {
      "battle_state": "{\"player\":{\"battle_info\":{\"max_hp\":80,\"current_hp\":74,\"block\":0,\"energy\":1,\"vulnerable_turns\":0,\"strength\":0,\"dexterity\":0,\"weak_turns\":0,\"frail_turns\":0,\"entangled_turns\":0,\"ritual\":0,\"rampage_damage\":0,\"artifact\":0,\"escaped\":false}},\"enemies\":[{\"enemy\":{\"Cultist\":{\"base_damage\":6,\"hp\":50,\"ritual_amount\":3,\"has_used_incantation\":true}},\"battle_info\":{\"max_hp\":50,\"current_hp\":0,\"block\":0,\"energy\":0,\"vulnerable_turns\":2,\"strength\":3,\"dexterity\":0,\"weak_turns\":0,\"frail_turns\":0,\"entangled_turns\":0,\"ritual\":3,\"rampage_damage\":0,\"artifact\":0,\"escaped\":false}}],\"cards\":{\"deck\":{\"cards\":[{\"card_enum\":\"Bash\",\"cost\":2,\"card_class\":{\"IronClad\":[\"Basic\",\"Attack\"]},\"effects\":[{\"AttackToTarget\":{\"amount\":8,\"num_attacks\":1,\"strength_multiplier\":1}},{\"ApplyVulnerable\":{\"duration\":2}}],\"upgrade_level\":0,\"play_condition\":\"True\",\"ethereal\":false,\"on_exhaust\":null,\"end_of_turn\":null,\"is_removable\":true,\"is_innate\":false,\"modified_cost_this_turn\":null},{\"card_enum\":\"Defend\",\"cost\":1,\"card_class\":{\"IronClad\":[\"Basic\",\"Skill\"]},\"effects\":[{\"GainDefense\":{\"amount\":5}}],\"upgrade_level\":0,\"play_condition\":\"True\",\"ethereal\":false,\"on_exhaust\":null,\"end_of_turn\":null,\"is_removable\":true,\"is_innate\":false,\"modified_cost_this_turn\":null},{\"card_enum\":\"Strike\",\"cost\":1,\"card_class\":{\"IronClad\":[\"Basic\",\"Attack\"]},\"effects\":[{\"AttackToTarget\":{\"amount\":6,\"num_attacks\":1,\"strength_multiplier\":1}}],\"upgrade_level\":0,\"play_condition\":\"True\",\"ethereal\":false,\"on_exhaust\":null,\"end_of_turn\":null,\"is_removable\":true,\"is_innate\":false,\"modified_cost_this_turn\":null},{\"card_enum\":\"Defend\",\"cost\":1,\"card_class\":{\"IronClad\":[\"Basic\",\"Skill\"]},\"effects\":[{\"GainDefense\":{\"amount\":5}}],\"upgrade_level\":0,\"play_condition\":\"True\",\"ethereal\":false,\"on_exhaust\":null,\"end_of_turn\":null,\"is_removable\":true,\"is_innate\":false,\"modified_cost_this_turn\":null}]},\"hand\":[{\"card_enum\":\"Strike\",\"cost\":1,\"card_class\":{\"IronClad\":[\"Basic\",\"Attack\"]},\"effects\":[{\"AttackToTarget\":{\"amount\":6,\"num_attacks\":1,\"strength_multiplier\":1}}],\"upgrade_level\":0,\"play_condition\":\"True\",\"ethereal\":false,\"on_exhaust\":null,\"end_of_turn\":null,\"is_removable\":true,\"is_innate\":false,\"modified_cost_this_turn\":null},{\"card_enum\":\"Defend\",\"cost\":1,\"card_class\":{\"IronClad\":[\"Basic\",\"Skill\"]},\"effects\":[{\"GainDefense\":{\"amount\":5}}],\"upgrade_level\":0,\"play_condition\":\"True\",\"ethereal\":false,\"on_exhaust\":null,\"end_of_turn\":null,\"is_removable\":true,\"is_innate\":false,\"modified_cost_this_turn\":null},{\"card_enum\":\"Defend\",\"cost\":1,\"card_class\":{\"IronClad\":[\"Basic\",\"Skill\"]},\"effects\":[{\"GainDefense\":{\"amount\":5}}],\"upgrade_level\":0,\"play_condition\":\"True\",\"ethereal\":false,\"on_exhaust\":null,\"end_of_turn\":null,\"is_removable\":true,\"is_innate\":false,\"modified_cost_this_turn\":null}],\"discard_pile\":[{\"card_enum\":\"Strike\",\"cost\":1,\"card_class\":{\"IronClad\":[\"Basic\",\"Attack\"]},\"effects\":[{\"AttackToTarget\":{\"amount\":6,\"num_attacks\":1,\"strength_multiplier\":1}}],\"upgrade_level\":0,\"play_condition\":\"True\",\"ethereal\":false,\"on_exhaust\":null,\"end_of_turn\":null,\"is_removable\":true,\"is_innate\":false,\"modified_cost_this_turn\":null},{\"card_enum\":\"Strike\",\"cost\":1,\"card_class\":{\"IronClad\":[\"Basic\",\"Attack\"]},\"effects\":[{\"AttackToTarget\":{\"amount\":6,\"num_attacks\":1,\"strength_multiplier\":1}}],\"upgrade_level\":0,\"play_condition\":\"True\",\"ethereal\":false,\"on_exhaust\":null,\"end_of_turn\":null,\"is_removable\":true,\"is_innate\":false,\"modified_cost_this_turn\":null}],\"exhausted\":[]},\"event_listeners\":[],\"global_info\":{\"ascention\":0,\"current_floor\":1},\"enemy_actions\":[[{\"Cultist\":\"DarkStrike\"},[{\"AttackToTarget\":{\"amount\":6,\"num_attacks\":1,\"strength_multiplier\":1}}]]],\"relics\":[],\"powers\":[],\"effect_queue\":[],\"battle_state\":\"PlayerTurn\",\"gold_stolen\":0,\"battle_events\":[],\"potions\":{\"potions\":[null,null,null],\"max_slots\":3},\"to_be_discarded\":[]}",
      "reward": 74,
      "battle_outcome": "victory",
      "final_hp": 74,
      "max_hp": 80,
      "steps_taken": 8,
      "env_name": "cultist",
      "max_steps": 20
    }
  ]
}